lp_show_my_bugs
