Metadata-Version: 1.1
Name: lp-show-my-bugs
Version: 0.0.4
Summary: UNKNOWN
Home-page: UNKNOWN
Author: Jorge Niedbalski R.
Author-email: jnr@metaklass.org
License: BSD
Platform: UNKNOWN
Classifier: Development Status :: 3 - Alpha
